{
  "id": "77ce6f6e-b506-410c-bdc5-07a63f910d9d",
  "prevId": "00000000-0000-0000-0000-000000000000",
  "version": "7",
  "dialect": "postgresql",
  "tables": {
    "public.ai_analyses": {
      "name": "ai_analyses",
      "schema": "",
      "columns": {
        "id": {
          "name": "id",
          "type": "serial",
          "primaryKey": true,
          "notNull": true
        },
        "repository_id": {
          "name": "repository_id",
          "type": "integer",
          "primaryKey": false,
          "notNull": true
        },
        "alternatives": {
          "name": "alternatives",
          "type": "jsonb",
          "primaryKey": false,
          "notNull": false
        },
        "category": {
          "name": "category",
          "type": "varchar(255)",
          "primaryKey": false,
          "notNull": false
        },
        "analysis_content": {
          "name": "analysis_content",
          "type": "text",
          "primaryKey": false,
          "notNull": false
        },
        "created_at": {
          "name": "created_at",
          "type": "timestamp",
          "primaryKey": false,
          "notNull": true,
          "default": "now()"
        }
      },
      "indexes": {},
      "foreignKeys": {
        "ai_analyses_repository_id_repositories_id_fk": {
          "name": "ai_analyses_repository_id_repositories_id_fk",
          "tableFrom": "ai_analyses",
          "tableTo": "repositories",
          "columnsFrom": [
            "repository_id"
          ],
          "columnsTo": [
            "id"
          ],
          "onDelete": "cascade",
          "onUpdate": "no action"
        }
      },
      "compositePrimaryKeys": {},
      "uniqueConstraints": {},
      "policies": {},
      "checkConstraints": {},
      "isRLSEnabled": false
    },
    "public.repositories": {
      "name": "repositories",
      "schema": "",
      "columns": {
        "id": {
          "name": "id",
          "type": "serial",
          "primaryKey": true,
          "notNull": true
        },
        "owner": {
          "name": "owner",
          "type": "varchar(255)",
          "primaryKey": false,
          "notNull": true
        },
        "name": {
          "name": "name",
          "type": "varchar(255)",
          "primaryKey": false,
          "notNull": true
        },
        "full_name": {
          "name": "full_name",
          "type": "varchar(511)",
          "primaryKey": false,
          "notNull": true
        },
        "description": {
          "name": "description",
          "type": "text",
          "primaryKey": false,
          "notNull": false
        },
        "github_url": {
          "name": "github_url",
          "type": "varchar(2048)",
          "primaryKey": false,
          "notNull": true
        },
        "avatar_url": {
          "name": "avatar_url",
          "type": "varchar(2048)",
          "primaryKey": false,
          "notNull": false
        },
        "primary_language": {
          "name": "primary_language",
          "type": "varchar(100)",
          "primaryKey": false,
          "notNull": false
        },
        "stars": {
          "name": "stars",
          "type": "integer",
          "primaryKey": false,
          "notNull": false,
          "default": 0
        },
        "forks": {
          "name": "forks",
          "type": "integer",
          "primaryKey": false,
          "notNull": false,
          "default": 0
        },
        "created_at": {
          "name": "created_at",
          "type": "timestamp",
          "primaryKey": false,
          "notNull": true,
          "default": "now()"
        },
        "updated_at": {
          "name": "updated_at",
          "type": "timestamp",
          "primaryKey": false,
          "notNull": true,
          "default": "now()"
        }
      },
      "indexes": {
        "full_name_idx": {
          "name": "full_name_idx",
          "columns": [
            {
              "expression": "full_name",
              "isExpression": false,
              "asc": true,
              "nulls": "last"
            }
          ],
          "isUnique": true,
          "concurrently": false,
          "method": "btree",
          "with": {}
        }
      },
      "foreignKeys": {},
      "compositePrimaryKeys": {},
      "uniqueConstraints": {
        "repositories_full_name_unique": {
          "name": "repositories_full_name_unique",
          "nullsNotDistinct": false,
          "columns": [
            "full_name"
          ]
        }
      },
      "policies": {},
      "checkConstraints": {},
      "isRLSEnabled": false
    }
  },
  "enums": {},
  "schemas": {},
  "sequences": {},
  "roles": {},
  "policies": {},
  "views": {},
  "_meta": {
    "columns": {},
    "schemas": {},
    "tables": {}
  }
}